font_icons/__init__.py
font_icons/admin.py
font_icons/choices.py
font_icons/fields.py
font_icons/models.py
font_icons/widget.py
font_icons/management/__init__.py
font_icons/management/commands/__init__.py
font_icons/management/commands/loadfontawesome5_free.py
font_icons/migrations/0001_initial.py
font_icons/migrations/0002_fonticonmodel_active.py
font_icons/migrations/0003_auto_20190304_1154.py
font_icons/migrations/__init__.py
font_icons/static/font_icons/admin_overrides.css
font_icons/templates/font_icons/select.html
django_font_icons-1.0.1.dist-info/LICENSE
django_font_icons-1.0.1.dist-info/METADATA
django_font_icons-1.0.1.dist-info/WHEEL
django_font_icons-1.0.1.dist-info/top_level.txt
django_font_icons-1.0.1.dist-info/RECORD
