Metadata-Version: 2.1
Name: django-font-icons
Version: 1.0.1
Summary: A utility for using icons in models and forms.
Home-page: https://github.com/JostCrow/django-font-icons
Author: Jorik Kraaikamp
Author-email: jorikkraaikamp@gmail.com
License: BSD License
Platform: UNKNOWN
Classifier: Environment :: Web Environment
Classifier: Framework :: Django
Classifier: Intended Audience :: Developers
Classifier: License :: OSI Approved :: BSD License
Classifier: Operating System :: OS Independent
Classifier: Topic :: Utilities
Requires-Dist: django (>1.11)
Requires-Dist: django-choices
